pygeonhole/__init__.py
pygeonhole/amazon_sender.py
pygeonhole/data_accessor.py
pygeonhole/data_accessor_bak.py
pygeonhole/ddb_kids.py
pygeonhole/ddb_runs.py
pygeonhole/ddb_slurps.py
pygeonhole/ddb_to_be_slurped.py
pygeonhole/dynamo.py
pygeonhole/khan_logger.py
pygeonhole/local.py
pygeonhole/ms_logger.py
pygeonhole/parseyaml2json.py
pygeonhole/s3.py
pygeonhole/utils.py
pygeonhole-0.0.3.dist-info/LICENSE
pygeonhole-0.0.3.dist-info/METADATA
pygeonhole-0.0.3.dist-info/WHEEL
pygeonhole-0.0.3.dist-info/top_level.txt
pygeonhole-0.0.3.dist-info/RECORD
