Metadata-Version: 2.1
Name: pygeonhole
Version: 0.0.3
Summary: Persistence and serialization tools
Home-page: https://github.com/thorwhalen/newut/tree/master/pygeonhole
Author: Thor Whalen
License: mit
Platform: any
License-File: LICENSE
